gnss-models/__init__.py
gnss-models/__main__.py
gnss-models/model_evaluation.py
gnss-models/model_generation.py
gnss-models/model_plotting.py
gnss-models/objective.py
gnss-models/run.py
gnss-models/save_pdf.py
gnss-models/utils.py
gnss_models/__init__.py
gnss_models/__main__.py
gnss_models/cli.py
gnss_models/model_evaluation.py
gnss_models/model_generation.py
gnss_models/model_plotting.py
gnss_models/objective.py
gnss_models/save_pdf.py
gnss_models/utils.py
gnss_models-0.1.4.dist-info/LICENSE
gnss_models-0.1.4.dist-info/METADATA
gnss_models-0.1.4.dist-info/WHEEL
gnss_models-0.1.4.dist-info/top_level.txt
gnss_models-0.1.4.dist-info/RECORD
