Metadata-Version: 2.1
Name: gnss-models
Version: 0.1.4
Summary: Tool to generate and evaluate mathematical models from GNSS satellites u-center csv files
Home-page: https://github.com/MelvinMartins/gnss-models
Author: Melvin Martins from NIST IT Lab
Author-email: melvin.martins@nist.gov
License: UNKNOWN
Platform: UNKNOWN
License-File: LICENSE
Requires-Dist: pandas (~=1.1.5)
Requires-Dist: setuptools (~=58.0.4)
Requires-Dist: julian (~=0.14)
Requires-Dist: numpy (~=1.19.5)
Requires-Dist: bokeh (~=2.3.2)
Requires-Dist: seaborn (~=0.11.2)
Requires-Dist: matplotlib (~=3.3.4)
Requires-Dist: scipy (~=1.5.4)
Requires-Dist: datashader (~=0.13.0)
Requires-Dist: sklearn (~=0.0)
Requires-Dist: scikit-learn (~=0.24.2)
Requires-Dist: fpdf2 (==2.5.7)
Requires-Dist: typer (==0.6.1)
